README
setup.py
censored_regression/__init__.py
censored_regression/base_estimator.py
censored_regression/lasso.py
censored_regression/least_squares.py
censored_regression.egg-info/PKG-INFO
censored_regression.egg-info/SOURCES.txt
censored_regression.egg-info/dependency_links.txt
censored_regression.egg-info/top_level.txt
tests/test_lasso.py
tests/test_least_squares.py