Metadata-Version: 1.1
Name: censored-regression
Version: 0.0.1
Summary: Linear regression where some of the labels are lower bounds
Home-page: http://packages.python.org/censored_regression
Author: Alex Rubinsteyn
Author-email: alex.rubinsteyn@gmail.com
License: Apache 2.0
Keywords: linear regression survival censored
Platform: UNKNOWN
Classifier: Development Status :: 3 - Alpha
Classifier: License :: OSI Approved :: Apache Software License
Classifier: Topic :: Scientific/Engineering
Classifier: Intended Audience :: Developers
Classifier: Intended Audience :: Science/Research
Classifier: Programming Language :: Python :: 2.7
